{
  "moduleList": [
    {
      "name": "我的课程",
      "type": "grid",
      "tabList": [
        {
          "name": "我的订单",
          "remark": "",
          "icon": "user_center_icon_order_wait_payment",
          "path": "/order/OrderListActivity",
          "params": 0,
          "jumpType": "arouter"
        },
        {
          "name": "我的合同",
          "remark": "",
          "icon": "user_center_icon_order_wait_sent_out",
          "path": "/order/ContractListActivity",
          "params": 1,
          "jumpType": "arouter"
        },
        {
          "name": "我的收藏",
          "remark": "",
          "icon": "user_center_icon_order_shouchang",
          "path": "/order/ProductCollectActivity",
          "params": 1,
          "jumpType": "arouter"
        },{
          "name": "我的评论",
          "remark": "",
          "icon": "user_center_icon_order_shouchang",
          "path": "/order/MyEvaluationActivity",
          "params": 1,
          "jumpType": "arouter"
        }
      ]
    },


    {
      "name": "",
      "type": "vertical",
      "tabList": [
        {
          "name": "修改密码",
          "remark": "",
          "icon": "user_center_icon_modify_pwd",
          "path": "/login/ModifyPwdActivity",
          "jumpType": "arouter"
        },
        {
          "name": "地址管理",
          "remark": "",
          "icon": "user_center_icon_usercenter_address_manager",
          "path": "/userCenter/AddressManagerActivity",
          "jumpType": "arouter"
        },

        {
          "name": "意见反馈",
          "remark": "",
          "icon": "user_center_icon_usercenter_address_manager",
          "path": "/order/FeedBackActivity",
          "jumpType": "arouter"
        },
        {
          "name": "常见问题",
          "remark": "",
          "icon": "user_center_icon_faq",
          "path": "http://faq.hebaopro.com",
          "jumpType": "url"
        },
        {
          "name": "关于我们",
          "remark": "",
          "icon": "user_center_icon_about_us",
          "path": "/userCenter/AboutUsActivity",
          "jumpType": "arouter"
        }
      ]
    }
  ]
}